check_python_versions/__init__.py
check_python_versions/__main__.py
check_python_versions/cli.py
check_python_versions/utils.py
check_python_versions/versions.py
check_python_versions/parsers/__init__.py
check_python_versions/parsers/classifiers.py
check_python_versions/parsers/ini.py
check_python_versions/parsers/poetry_version_spec.py
check_python_versions/parsers/python.py
check_python_versions/parsers/requires_python.py
check_python_versions/parsers/yaml.py
check_python_versions/sources/__init__.py
check_python_versions/sources/all.py
check_python_versions/sources/appveyor.py
check_python_versions/sources/base.py
check_python_versions/sources/github.py
check_python_versions/sources/manylinux.py
check_python_versions/sources/pyproject.py
check_python_versions/sources/setup_py.py
check_python_versions/sources/tox.py
check_python_versions/sources/travis.py
check_python_versions-0.24.0.dist-info/licenses/LICENSE
check_python_versions-0.24.0.dist-info/METADATA
check_python_versions-0.24.0.dist-info/WHEEL
check_python_versions-0.24.0.dist-info/entry_points.txt
check_python_versions-0.24.0.dist-info/top_level.txt
check_python_versions-0.24.0.dist-info/RECORD
