Metadata-Version: 2.4
Name: check-python-versions
Version: 0.24.0
Summary: Compare supported Python versions in setup.py vs tox.ini et al.
Home-page: https://github.com/mgedmin/check-python-versions
Author: Marius Gedminas
Author-email: marius@gedmin.as
License: GPL-3.0-or-later
Project-URL: Changelog, https://github.com/mgedmin/check-python-versions/blob/master/CHANGES.rst
Project-URL: Issues, https://github.com/mgedmin/check-python-versions/issues
Project-URL: Source Code, https://github.com/mgedmin/check-python-versions
Keywords: python packaging version checker linter setup.py tox travis appveyor
Classifier: Development Status :: 4 - Beta
Classifier: Environment :: Console
Classifier: Intended Audience :: Developers
Classifier: Operating System :: OS Independent
Classifier: Programming Language :: Python :: 3.10
Classifier: Programming Language :: Python :: 3.11
Classifier: Programming Language :: Python :: 3.12
Classifier: Programming Language :: Python :: 3.13
Classifier: Programming Language :: Python :: 3.14
Classifier: Programming Language :: Python :: Implementation :: CPython
Classifier: Programming Language :: Python :: Implementation :: PyPy
Requires-Python: >=3.10
License-File: LICENSE
Requires-Dist: pyyaml
Requires-Dist: tomlkit
Dynamic: author
Dynamic: author-email
Dynamic: classifier
Dynamic: description
Dynamic: description-content-type
Dynamic: home-page
Dynamic: keywords
Dynamic: license
Dynamic: license-file
Dynamic: project-url
Dynamic: requires-dist
Dynamic: requires-python
Dynamic: summary
